mirapy/__init__.py
mirapy/_astropy_init.py
mirapy/conftest.py
mirapy/version.py
mirapy/__pycache__/__init__.cpython-36.pyc
mirapy/__pycache__/_astropy_init.cpython-36.pyc
mirapy/__pycache__/version.cpython-36.pyc
mirapy/autoencoder/__init__.py
mirapy/autoencoder/models.py
mirapy/autoencoder/__pycache__/__init__.cpython-36.pyc
mirapy/autoencoder/__pycache__/models.cpython-36.pyc
mirapy/classifiers/__init__.py
mirapy/classifiers/models.py
mirapy/classifiers/__pycache__/__init__.cpython-36.pyc
mirapy/classifiers/__pycache__/models.cpython-36.pyc
mirapy/data/README.rst
mirapy/data/load_dataset.py
mirapy/example_subpkg/__init__.py
mirapy/example_subpkg/setup_package.py
mirapy/example_subpkg/tests/__init__.py
mirapy/extern/__init__.py
mirapy/fitting/__init__.py
mirapy/fitting/losses.py
mirapy/fitting/models.py
mirapy/fitting/optimizers.py
mirapy/fitting/__pycache__/__init__.cpython-36.pyc
mirapy/fitting/__pycache__/losses.cpython-36.pyc
mirapy/fitting/__pycache__/models.cpython-36.pyc
mirapy/fitting/__pycache__/optimizers.cpython-36.pyc
mirapy/fitting/tests/__init__.py
mirapy/fitting/tests/test_models.py
mirapy/fitting/tests/test_optimizers.py
mirapy/tests/__init__.py
mirapy/tests/coveragerc
mirapy/tests/setup_package.py
mirapy/utils/__init__.py
mirapy/utils/utils.py
mirapy/utils/__pycache__/__init__.cpython-36.pyc
mirapy/utils/tests/__init__.py
mirapy/visualization/__init__.py
mirapy/visualization/visualize.py
mirapy-0.1.0.dist-info/LICENSE.rst
mirapy-0.1.0.dist-info/METADATA
mirapy-0.1.0.dist-info/WHEEL
mirapy-0.1.0.dist-info/entry_points.txt
mirapy-0.1.0.dist-info/top_level.txt
mirapy-0.1.0.dist-info/RECORD
