Metadata-Version: 2.1
Name: mirapy
Version: 0.1.0
Summary: Python package for Deep Learning in Astronomy
Home-page: https://github.com/swapsha96/MiraPy
Author: Swapnil Sharma, Akhil Singhal
Author-email: swap.sha96@gmail.com, akhilsinghal1234@gmail.com
License: MIT
Platform: UNKNOWN
Requires-Python: >=3.5
Requires-Dist: astropy
Requires-Dist: numpy (>=1.11.0)
Requires-Dist: scipy (>=0.18.0)
Requires-Dist: matplotlib (>=1.3)
Requires-Dist: autograd
